varv/__init__.py
varv/accessor.py
varv/base.py
varv/config.py
varv/dataset.py
varv/events.py
varv/utils.py
varv/widgets.py
varv/classification/__init__.py
varv/classification/predictdna.py
varv/classification/predictdna_cv.py
varv/classification/assets/DNA_6mer_prediction_model.csv
varv/classification/assets/DNA_6mer_prediction_model_backup.csv
varv/classification/assets/DNA_6mer_prediction_model_cv.csv
varv/feature_extraction/__init__.py
varv/feature_extraction/dimreduction.py
varv/feature_extraction/recombination_filter.py
varv/feature_extraction/removal_filter.py
varv/feature_extraction/assets/calibration_metrics.json
varv/feature_extraction/assets/principal_components_dna.npy
varv/feature_extraction/assets/recombination_calibration_pipe.pkl
varv/feature_extraction/assets/recombination_clf_state_dict.zip
varv/feature_extraction/assets/recombination_preprocessing_pipe.pkl
varv/feature_extraction/assets/recombination_svm_confusion_matrix.csv
varv/feature_extraction/assets/recombination_svm_info.txt
varv/feature_extraction/assets/removal_svm.pkl
varv/feature_extraction/assets/removal_svm_confusion_matrix.csv
varv/feature_extraction/assets/removal_svm_info.txt
varv/io/__init__.py
varv/io/labview.py
varv/preprocessing/__init__.py
varv/preprocessing/capcomp.py
varv/preprocessing/capnorm.py
varv/preprocessing/changepoint.py
varv/preprocessing/changepoint_cv.py
varv/preprocessing/cpic.py
varv/preprocessing/eventdetection.py
varv/preprocessing/assets/equal_spacing_dna.npz
varv/preprocessing/assets/principal_components_for_level_finding.npy
varv-0.0.2.dist-info/METADATA
varv-0.0.2.dist-info/WHEEL
varv-0.0.2.dist-info/licenses/COPYING
varv-0.0.2.dist-info/RECORD
