Metadata-Version: 2.4
Name: varv
Version: 0.0.2
Summary: Python module for processing of variable bias voltage nanopore sequencing
Project-URL: Repository, https://gitlab.tudelft.nl/xiuqichen/varv.git
Project-URL: Issues, https://gitlab.tudelft.nl/xiuqichen/varv/-/issues
Author-email: Thijn Hoekstra <t.w.hoekstra@student.tudelft.nl>, Xiuqi Chen <X.Chen-13@tudelft.nl>
License:                     GNU GENERAL PUBLIC LICENSE
License-File: COPYING
Keywords: Lobster Thermidor,bias voltage,bioinformatics,nanopore,peptide
Classifier: Development Status :: 3 - Alpha
Classifier: Intended Audience :: Developers
Classifier: Programming Language :: Python :: 3.13
Requires-Python: >=3.13
Requires-Dist: dtw-python>=1.5.3
Requires-Dist: h5py>=3.12.1
Requires-Dist: matplotlib>=3.9.2
Requires-Dist: numpy>=2.1.0
Requires-Dist: pandas>=2.2.2
Requires-Dist: scikit-learn==1.6.1
Requires-Dist: scipy>=1.14.1
Requires-Dist: tables>=3.10.1
Requires-Dist: torch>=2.6.0
Requires-Dist: tqdm>=4.66.5
Provides-Extra: dev
Requires-Dist: pytest-cov>=6.0.0; extra == 'dev'
Requires-Dist: pytest>=8.3.3; extra == 'dev'
Requires-Dist: ruff>=0.11.2; extra == 'dev'
Requires-Dist: sphinx-rtd-theme>=3.0.2; extra == 'dev'
Requires-Dist: sphinx>=8.1.3; extra == 'dev'
Provides-Extra: docs
Requires-Dist: sphinx-rtd-theme>=3.0.2; extra == 'docs'
Requires-Dist: sphinx>=8.1.3; extra == 'docs'
Provides-Extra: lint
Requires-Dist: ruff>=0.11.2; extra == 'lint'
Provides-Extra: test
Requires-Dist: pytest-cov>=6.0.0; extra == 'test'
Requires-Dist: pytest>=8.3.3; extra == 'test'
Provides-Extra: widget
Requires-Dist: ipympl>=0.9.4; extra == 'widget'
Requires-Dist: ipywidgets>=8.1.5; extra == 'widget'
Requires-Dist: jupyterlab>=4.3.0; extra == 'widget'
